{
  "empty": {
    "status": {
      "statusCode": 200,
      "success": true
    },
    "result": []
  },
  "success": {
    "status": {
      "statusCode": 200,
      "success": true
    },
    "result": [
      {
        "id": "f9b97a1b-a344-4bb7-a712-ce76fbdffae6",
        "userId": 801,
        "email": "user801@testmail.com",
        "userName": "test801",
        "firstName": "Veronica",
        "lastName": "Atkins",
        "migrated": false,
        "migratedDate": "Sun Aug 16 2020 20:43:56 GMT-0500 (Colombia Standard Time)"
      },
      {
        "id": "19c76b1d-17dc-40d6-8ff8-2e5905d12d47",
        "userId": 802,
        "email": "user802@testmail.com",
        "userName": "test802",
        "firstName": "Rivera",
        "lastName": "Vaughn",
        "migrated": true,
        "migratedDate": "Sat Oct 24 2020 09:44:36 GMT-0500 (Colombia Standard Time)"
      },
      {
        "id": "88074834-f548-4b9c-880a-290b68e8c83c",
        "userId": 803,
        "email": "user803@testmail.com",
        "userName": "test803",
        "firstName": "Socorro",
        "lastName": "Vargas",
        "migrated": true,
        "migratedDate": "Thu Jan 07 2021 16:43:21 GMT-0500 (Colombia Standard Time)"
      },
      {
        "id": "6fe830e2-d67b-4625-8523-9e5952bd8b33",
        "userId": 804,
        "email": "user804@testmail.com",
        "userName": "test804",
        "firstName": "Beatrice",
        "lastName": "Knapp",
        "migrated": true,
        "migratedDate": "Mon Oct 26 2020 05:20:02 GMT-0500 (Colombia Standard Time)"
      },
      {
        "id": "300f6ebd-a0b6-4e2a-af6c-315c3b9f24ab",
        "userId": 805,
        "email": "user805@testmail.com",
        "userName": "test805",
        "firstName": "Vilma",
        "lastName": "Eaton",
        "migrated": true,
        "migratedDate": "Mon Jul 20 2020 22:13:04 GMT-0500 (Colombia Standard Time)"
      },
      {
        "id": "853b2222-2fd2-4ab5-b154-888f877ee992",
        "userId": 806,
        "email": "user806@testmail.com",
        "userName": "test806",
        "firstName": "Jeri",
        "lastName": "Huber",
        "migrated": true,
        "migratedDate": "Tue Sep 15 2020 06:59:45 GMT-0500 (Colombia Standard Time)"
      },
      {
        "id": "a900a0fd-7e45-471c-9acc-1448650114d4",
        "userId": 807,
        "email": "user807@testmail.com",
        "userName": "test807",
        "firstName": "Tonia",
        "lastName": "Ruiz",
        "migrated": true,
        "migratedDate": "Tue Feb 18 2020 00:42:06 GMT-0500 (Colombia Standard Time)"
      },
      {
        "id": "8c4f04de-58d4-4c1b-8ffd-d5215536090e",
        "userId": 808,
        "email": "user808@testmail.com",
        "userName": "test808",
        "firstName": "Kitty",
        "lastName": "Randolph",
        "migrated": false,
        "migratedDate": "Thu Sep 10 2020 23:48:06 GMT-0500 (Colombia Standard Time)"
      },
      {
        "id": "24e0f864-cc19-40cc-9344-74d5d3a5edfd",
        "userId": 809,
        "email": "user809@testmail.com",
        "userName": "test809",
        "firstName": "Georgia",
        "lastName": "Guerrero",
        "migrated": false,
        "migratedDate": "Wed May 19 2021 20:11:49 GMT-0500 (Colombia Standard Time)"
      },
      {
        "id": "2ca9050d-3a88-41b5-8f58-1651dc888dbb",
        "userId": 810,
        "email": "user810@testmail.com",
        "userName": "test810",
        "firstName": "Desiree",
        "lastName": "Benson",
        "migrated": true,
        "migratedDate": "Thu Apr 16 2020 19:22:41 GMT-0500 (Colombia Standard Time)"
      },
      {
        "id": "8012d5c7-cc6f-4e94-aeda-5e96bdf9f2cc",
        "userId": 811,
        "email": "user811@testmail.com",
        "userName": "test811",
        "firstName": "Amalia",
        "lastName": "Peters",
        "migrated": true,
        "migratedDate": "Mon Mar 02 2020 14:13:02 GMT-0500 (Colombia Standard Time)"
      },
      {
        "id": "9a6248f5-d2ab-47e1-8968-80e35b073058",
        "userId": 812,
        "email": "user812@testmail.com",
        "userName": "test812",
        "firstName": "Maryanne",
        "lastName": "Carver",
        "migrated": true,
        "migratedDate": "Mon Jun 15 2020 11:27:15 GMT-0500 (Colombia Standard Time)"
      },
      {
        "id": "f1dd9422-9179-47d7-b095-42ec197dcb6f",
        "userId": 813,
        "email": "user813@testmail.com",
        "userName": "test813",
        "firstName": "Lea",
        "lastName": "Bender",
        "migrated": false,
        "migratedDate": "Wed Jan 06 2021 16:54:32 GMT-0500 (Colombia Standard Time)"
      },
      {
        "id": "a4fa8bd7-1fd1-42ac-9ca8-43f53df4d486",
        "userId": 814,
        "email": "user814@testmail.com",
        "userName": "test814",
        "firstName": "Sara",
        "lastName": "Banks",
        "migrated": false,
        "migratedDate": "Fri May 21 2021 16:07:46 GMT-0500 (Colombia Standard Time)"
      },
      {
        "id": "4bc8a9d7-e6a4-40ec-a7f8-c2c07e304a7d",
        "userId": 815,
        "email": "user815@testmail.com",
        "userName": "test815",
        "firstName": "Gilda",
        "lastName": "Pittman",
        "migrated": true,
        "migratedDate": "Tue Feb 04 2020 20:23:56 GMT-0500 (Colombia Standard Time)"
      },
      {
        "id": "2676121f-ba98-4b81-81e3-5fc3c3bfaeb7",
        "userId": 816,
        "email": "user816@testmail.com",
        "userName": "test816",
        "firstName": "Moon",
        "lastName": "Harris",
        "migrated": true,
        "migratedDate": "Fri Sep 25 2020 13:05:46 GMT-0500 (Colombia Standard Time)"
      },
      {
        "id": "f659c77a-30ad-47c5-98df-d07e5cf2f4e1",
        "userId": 817,
        "email": "user817@testmail.com",
        "userName": "test817",
        "firstName": "Lana",
        "lastName": "Grant",
        "migrated": true,
        "migratedDate": "Tue May 12 2020 23:14:00 GMT-0500 (Colombia Standard Time)"
      },
      {
        "id": "4e81661c-c788-4aa4-a484-1d41011777b9",
        "userId": 818,
        "email": "user818@testmail.com",
        "userName": "test818",
        "firstName": "Richmond",
        "lastName": "Baldwin",
        "migrated": true,
        "migratedDate": "Tue Jun 02 2020 06:27:10 GMT-0500 (Colombia Standard Time)"
      },
      {
        "id": "045746c7-6b9d-4042-842a-3211d1d59657",
        "userId": 819,
        "email": "user819@testmail.com",
        "userName": "test819",
        "firstName": "Mendoza",
        "lastName": "Drake",
        "migrated": false,
        "migratedDate": "Wed Jan 13 2021 14:35:32 GMT-0500 (Colombia Standard Time)"
      },
      {
        "id": "4320af67-b8ec-461c-b219-86e07598867c",
        "userId": 820,
        "email": "user820@testmail.com",
        "userName": "test820",
        "firstName": "Benita",
        "lastName": "Summers",
        "migrated": false,
        "migratedDate": "Fri Jan 01 2021 10:03:52 GMT-0500 (Colombia Standard Time)"
      },
      {
        "id": "45b516f6-7610-42fb-99cd-f7abd173799c",
        "userId": 821,
        "email": "user821@testmail.com",
        "userName": "test821",
        "firstName": "Stacey",
        "lastName": "Fowler",
        "migrated": false,
        "migratedDate": "Sun Mar 14 2021 01:24:37 GMT-0500 (Colombia Standard Time)"
      },
      {
        "id": "e5ad3a33-b3b5-4425-ad08-6fe0a2b6ff1e",
        "userId": 822,
        "email": "user822@testmail.com",
        "userName": "test822",
        "firstName": "Beach",
        "lastName": "Mcpherson",
        "migrated": true,
        "migratedDate": "Fri Jul 23 2021 03:00:45 GMT-0500 (Colombia Standard Time)"
      },
      {
        "id": "578ca6af-8bca-4042-b88c-6a861141e992",
        "userId": 823,
        "email": "user823@testmail.com",
        "userName": "test823",
        "firstName": "Vincent",
        "lastName": "Wagner",
        "migrated": true,
        "migratedDate": "Wed Mar 24 2021 15:22:04 GMT-0500 (Colombia Standard Time)"
      },
      {
        "id": "1cb3f152-d869-423e-b2f0-4b58c933f440",
        "userId": 824,
        "email": "user824@testmail.com",
        "userName": "test824",
        "firstName": "Valeria",
        "lastName": "Cross",
        "migrated": false,
        "migratedDate": "Wed Dec 16 2020 01:32:44 GMT-0500 (Colombia Standard Time)"
      },
      {
        "id": "8f434fad-2d58-4cfa-93eb-d433427a2e7b",
        "userId": 825,
        "email": "user825@testmail.com",
        "userName": "test825",
        "firstName": "Brandy",
        "lastName": "Love",
        "migrated": false,
        "migratedDate": "Wed Jun 30 2021 11:52:56 GMT-0500 (Colombia Standard Time)"
      },
      {
        "id": "de60f139-d40a-4b68-bc41-185c7086ccd7",
        "userId": 826,
        "email": "user826@testmail.com",
        "userName": "test826",
        "firstName": "Tabatha",
        "lastName": "Bond",
        "migrated": true,
        "migratedDate": "Sat Apr 11 2020 09:28:11 GMT-0500 (Colombia Standard Time)"
      },
      {
        "id": "747fa97e-b7e3-4ea5-bac8-be7f9332cc4d",
        "userId": 827,
        "email": "user827@testmail.com",
        "userName": "test827",
        "firstName": "Cabrera",
        "lastName": "Pope",
        "migrated": true,
        "migratedDate": "Tue Jan 05 2021 20:19:36 GMT-0500 (Colombia Standard Time)"
      },
      {
        "id": "69a838b7-4f06-4d74-9b08-d83d5c6aaa3b",
        "userId": 828,
        "email": "user828@testmail.com",
        "userName": "test828",
        "firstName": "Elaine",
        "lastName": "Suarez",
        "migrated": true,
        "migratedDate": "Mon Mar 02 2020 10:33:03 GMT-0500 (Colombia Standard Time)"
      },
      {
        "id": "7cac27a9-73a5-4e28-8e5a-ce9a467950df",
        "userId": 829,
        "email": "user829@testmail.com",
        "userName": "test829",
        "firstName": "Jefferson",
        "lastName": "Hale",
        "migrated": true,
        "migratedDate": "Thu Sep 24 2020 20:50:14 GMT-0500 (Colombia Standard Time)"
      },
      {
        "id": "d3a1bcc6-f753-42b4-b59d-32399795289a",
        "userId": 830,
        "email": "user830@testmail.com",
        "userName": "test830",
        "firstName": "Deirdre",
        "lastName": "Moody",
        "migrated": false,
        "migratedDate": "Mon Jul 20 2020 02:38:11 GMT-0500 (Colombia Standard Time)"
      },
      {
        "id": "9223bf86-4964-4494-bf03-3176801b189a",
        "userId": 831,
        "email": "user831@testmail.com",
        "userName": "test831",
        "firstName": "Madge",
        "lastName": "Battle",
        "migrated": false,
        "migratedDate": "Sun Oct 18 2020 23:38:38 GMT-0500 (Colombia Standard Time)"
      },
      {
        "id": "f67e7807-64b5-405b-ba74-578eca1dfa43",
        "userId": 832,
        "email": "user832@testmail.com",
        "userName": "test832",
        "firstName": "Romero",
        "lastName": "Moses",
        "migrated": true,
        "migratedDate": "Mon Feb 17 2020 22:09:50 GMT-0500 (Colombia Standard Time)"
      },
      {
        "id": "96f8dafd-3784-417d-819f-527095c987a8",
        "userId": 833,
        "email": "user833@testmail.com",
        "userName": "test833",
        "firstName": "Roth",
        "lastName": "Stout",
        "migrated": true,
        "migratedDate": "Sun Apr 25 2021 09:04:21 GMT-0500 (Colombia Standard Time)"
      },
      {
        "id": "60e24119-6cca-46d9-a8fd-bbe433dd0b68",
        "userId": 834,
        "email": "user834@testmail.com",
        "userName": "test834",
        "firstName": "Harmon",
        "lastName": "Hoover",
        "migrated": false,
        "migratedDate": "Sat Dec 26 2020 08:39:28 GMT-0500 (Colombia Standard Time)"
      },
      {
        "id": "e5f98ce0-2c70-45e5-b172-d8ab074842f8",
        "userId": 835,
        "email": "user835@testmail.com",
        "userName": "test835",
        "firstName": "Karyn",
        "lastName": "Conner",
        "migrated": true,
        "migratedDate": "Sun Mar 22 2020 20:56:34 GMT-0500 (Colombia Standard Time)"
      },
      {
        "id": "6b0835aa-5159-4be8-bab7-858f91f7ee42",
        "userId": 836,
        "email": "user836@testmail.com",
        "userName": "test836",
        "firstName": "Wall",
        "lastName": "Roberson",
        "migrated": false,
        "migratedDate": "Fri Nov 06 2020 09:30:42 GMT-0500 (Colombia Standard Time)"
      },
      {
        "id": "fb4f4659-7923-4692-988f-5f8be3f3580a",
        "userId": 837,
        "email": "user837@testmail.com",
        "userName": "test837",
        "firstName": "Battle",
        "lastName": "Vang",
        "migrated": false,
        "migratedDate": "Tue Nov 24 2020 22:21:57 GMT-0500 (Colombia Standard Time)"
      },
      {
        "id": "41307d0e-a489-42fa-9a6a-de1c16c63c41",
        "userId": 838,
        "email": "user838@testmail.com",
        "userName": "test838",
        "firstName": "Townsend",
        "lastName": "Ramirez",
        "migrated": true,
        "migratedDate": "Wed Jan 13 2021 04:28:49 GMT-0500 (Colombia Standard Time)"
      },
      {
        "id": "d17e5240-b006-4951-b6c1-c599990c8aa0",
        "userId": 839,
        "email": "user839@testmail.com",
        "userName": "test839",
        "firstName": "Rachel",
        "lastName": "Small",
        "migrated": true,
        "migratedDate": "Thu Jul 30 2020 01:10:55 GMT-0500 (Colombia Standard Time)"
      },
      {
        "id": "9737c07a-ca82-435c-845f-3458246ca170",
        "userId": 840,
        "email": "user840@testmail.com",
        "userName": "test840",
        "firstName": "Savage",
        "lastName": "Pace",
        "migrated": true,
        "migratedDate": "Mon Mar 29 2021 19:37:32 GMT-0500 (Colombia Standard Time)"
      },
      {
        "id": "855960d1-4d93-4396-b382-80a87468bc57",
        "userId": 841,
        "email": "user841@testmail.com",
        "userName": "test841",
        "firstName": "Darla",
        "lastName": "Stephens",
        "migrated": false,
        "migratedDate": "Sun Aug 02 2020 22:43:00 GMT-0500 (Colombia Standard Time)"
      },
      {
        "id": "f5ac7357-779c-4b29-a20b-ce6564d6bba1",
        "userId": 842,
        "email": "user842@testmail.com",
        "userName": "test842",
        "firstName": "Elba",
        "lastName": "Mathews",
        "migrated": false,
        "migratedDate": "Sun Dec 13 2020 11:39:27 GMT-0500 (Colombia Standard Time)"
      },
      {
        "id": "91b17163-bef2-4e8d-8932-5e3da95295fe",
        "userId": 843,
        "email": "user843@testmail.com",
        "userName": "test843",
        "firstName": "Andrea",
        "lastName": "Hartman",
        "migrated": false,
        "migratedDate": "Sat Jan 16 2021 08:20:47 GMT-0500 (Colombia Standard Time)"
      },
      {
        "id": "d1745a47-9428-4654-85e0-83c7e079cf34",
        "userId": 844,
        "email": "user844@testmail.com",
        "userName": "test844",
        "firstName": "Cherry",
        "lastName": "Knight",
        "migrated": false,
        "migratedDate": "Wed Apr 28 2021 15:43:11 GMT-0500 (Colombia Standard Time)"
      },
      {
        "id": "adec5574-95b0-4a5f-9534-7fce6bf626f9",
        "userId": 845,
        "email": "user845@testmail.com",
        "userName": "test845",
        "firstName": "Owen",
        "lastName": "Durham",
        "migrated": true,
        "migratedDate": "Fri Mar 05 2021 06:57:19 GMT-0500 (Colombia Standard Time)"
      },
      {
        "id": "6a380350-3cd7-4419-90c5-540ce84046a9",
        "userId": 846,
        "email": "user846@testmail.com",
        "userName": "test846",
        "firstName": "Hinton",
        "lastName": "Bird",
        "migrated": true,
        "migratedDate": "Mon Mar 22 2021 08:59:21 GMT-0500 (Colombia Standard Time)"
      },
      {
        "id": "f8803a13-3f3f-458d-ab78-03354759d351",
        "userId": 847,
        "email": "user847@testmail.com",
        "userName": "test847",
        "firstName": "Gentry",
        "lastName": "Riggs",
        "migrated": false,
        "migratedDate": "Sun Nov 22 2020 12:11:38 GMT-0500 (Colombia Standard Time)"
      },
      {
        "id": "1e409947-7411-4002-a85b-e93ae707f177",
        "userId": 848,
        "email": "user848@testmail.com",
        "userName": "test848",
        "firstName": "Frankie",
        "lastName": "Gutierrez",
        "migrated": true,
        "migratedDate": "Mon Nov 02 2020 21:15:37 GMT-0500 (Colombia Standard Time)"
      },
      {
        "id": "d3923e9f-88e7-48d0-9dde-aa8ecde1d0a7",
        "userId": 849,
        "email": "user849@testmail.com",
        "userName": "test849",
        "firstName": "Elsa",
        "lastName": "Cortez",
        "migrated": false,
        "migratedDate": "Fri Jan 15 2021 13:49:00 GMT-0500 (Colombia Standard Time)"
      },
      {
        "id": "604c8a6a-d231-4065-8c50-d42189656f67",
        "userId": 850,
        "email": "user850@testmail.com",
        "userName": "test850",
        "firstName": "Earline",
        "lastName": "Frye",
        "migrated": false,
        "migratedDate": "Tue Sep 15 2020 15:18:00 GMT-0500 (Colombia Standard Time)"
      },
      {
        "id": "e80e9533-93bc-4296-973b-5ef8397b96de",
        "userId": 851,
        "email": "user851@testmail.com",
        "userName": "test851",
        "firstName": "Albert",
        "lastName": "Dennis",
        "migrated": true,
        "migratedDate": "Wed Feb 12 2020 03:10:06 GMT-0500 (Colombia Standard Time)"
      },
      {
        "id": "3911c1c5-bbc3-4a45-ad6e-7b8831ad47e6",
        "userId": 852,
        "email": "user852@testmail.com",
        "userName": "test852",
        "firstName": "Robbie",
        "lastName": "Osborne",
        "migrated": false,
        "migratedDate": "Sun Feb 28 2021 23:11:44 GMT-0500 (Colombia Standard Time)"
      },
      {
        "id": "3f2b8a31-b261-4eff-9d00-20e1ecaad52c",
        "userId": 853,
        "email": "user853@testmail.com",
        "userName": "test853",
        "firstName": "Strong",
        "lastName": "Mooney",
        "migrated": true,
        "migratedDate": "Sun Apr 12 2020 04:28:22 GMT-0500 (Colombia Standard Time)"
      },
      {
        "id": "2f30d6b8-026d-4e73-88f4-d1e8a6f2fc82",
        "userId": 854,
        "email": "user854@testmail.com",
        "userName": "test854",
        "firstName": "Dean",
        "lastName": "Mcdaniel",
        "migrated": true,
        "migratedDate": "Sun Feb 14 2021 12:31:37 GMT-0500 (Colombia Standard Time)"
      },
      {
        "id": "50869b6f-6c36-4062-9997-ffc8d549a6f3",
        "userId": 855,
        "email": "user855@testmail.com",
        "userName": "test855",
        "firstName": "Shana",
        "lastName": "Chapman",
        "migrated": false,
        "migratedDate": "Mon May 25 2020 12:03:08 GMT-0500 (Colombia Standard Time)"
      },
      {
        "id": "1b3155c2-112e-4e65-89f0-6cb50d530dcd",
        "userId": 856,
        "email": "user856@testmail.com",
        "userName": "test856",
        "firstName": "Collier",
        "lastName": "Gould",
        "migrated": false,
        "migratedDate": "Mon Jun 21 2021 05:56:59 GMT-0500 (Colombia Standard Time)"
      },
      {
        "id": "aaa37794-1724-4575-837b-b950a1edeff0",
        "userId": 857,
        "email": "user857@testmail.com",
        "userName": "test857",
        "firstName": "Caroline",
        "lastName": "Roth",
        "migrated": true,
        "migratedDate": "Sat Jan 02 2021 18:22:10 GMT-0500 (Colombia Standard Time)"
      },
      {
        "id": "fba7f14a-bf65-4943-a1ab-7639fadb62a0",
        "userId": 858,
        "email": "user858@testmail.com",
        "userName": "test858",
        "firstName": "Kent",
        "lastName": "Cabrera",
        "migrated": false,
        "migratedDate": "Tue May 05 2020 09:20:28 GMT-0500 (Colombia Standard Time)"
      },
      {
        "id": "8fa8f891-31ee-4127-95d4-890423b7477e",
        "userId": 859,
        "email": "user859@testmail.com",
        "userName": "test859",
        "firstName": "Rose",
        "lastName": "Rivera",
        "migrated": false,
        "migratedDate": "Sat Mar 14 2020 02:06:19 GMT-0500 (Colombia Standard Time)"
      },
      {
        "id": "83a18097-9b4c-4e9f-a035-49084532fcd5",
        "userId": 860,
        "email": "user860@testmail.com",
        "userName": "test860",
        "firstName": "Carver",
        "lastName": "Reese",
        "migrated": true,
        "migratedDate": "Mon Feb 01 2021 23:15:02 GMT-0500 (Colombia Standard Time)"
      },
      {
        "id": "59070b61-e6b7-414e-9cdb-e5336d4192d8",
        "userId": 861,
        "email": "user861@testmail.com",
        "userName": "test861",
        "firstName": "Karen",
        "lastName": "Morgan",
        "migrated": true,
        "migratedDate": "Sat Oct 24 2020 11:51:06 GMT-0500 (Colombia Standard Time)"
      },
      {
        "id": "3fd09273-1588-4917-a64b-bcf6bc8084b4",
        "userId": 862,
        "email": "user862@testmail.com",
        "userName": "test862",
        "firstName": "Kristin",
        "lastName": "Porter",
        "migrated": true,
        "migratedDate": "Wed Aug 19 2020 15:31:00 GMT-0500 (Colombia Standard Time)"
      },
      {
        "id": "880c52b9-35d4-4b95-9c98-a0e73b84a614",
        "userId": 863,
        "email": "user863@testmail.com",
        "userName": "test863",
        "firstName": "Hooper",
        "lastName": "Burke",
        "migrated": true,
        "migratedDate": "Sat Aug 29 2020 08:21:33 GMT-0500 (Colombia Standard Time)"
      },
      {
        "id": "ac3ffcc1-0950-4333-a0b0-f6d16a5fcd81",
        "userId": 864,
        "email": "user864@testmail.com",
        "userName": "test864",
        "firstName": "Jasmine",
        "lastName": "Weber",
        "migrated": false,
        "migratedDate": "Mon Oct 12 2020 05:27:12 GMT-0500 (Colombia Standard Time)"
      },
      {
        "id": "cd218c00-fce7-4a03-9d94-a6627930a854",
        "userId": 865,
        "email": "user865@testmail.com",
        "userName": "test865",
        "firstName": "Lynn",
        "lastName": "Jenkins",
        "migrated": true,
        "migratedDate": "Fri Aug 07 2020 02:58:51 GMT-0500 (Colombia Standard Time)"
      },
      {
        "id": "52fb9978-ff89-43db-8e08-07ff455cd9d5",
        "userId": 866,
        "email": "user866@testmail.com",
        "userName": "test866",
        "firstName": "Carlson",
        "lastName": "Haynes",
        "migrated": true,
        "migratedDate": "Fri Oct 16 2020 08:03:29 GMT-0500 (Colombia Standard Time)"
      },
      {
        "id": "ce348e0c-fc3a-4eaa-9e0d-b3c320eb2c39",
        "userId": 867,
        "email": "user867@testmail.com",
        "userName": "test867",
        "firstName": "Jane",
        "lastName": "Richard",
        "migrated": true,
        "migratedDate": "Fri Jun 11 2021 07:53:07 GMT-0500 (Colombia Standard Time)"
      },
      {
        "id": "bd1450aa-ded0-4d16-a57c-0e5feb550fa9",
        "userId": 868,
        "email": "user868@testmail.com",
        "userName": "test868",
        "firstName": "Wells",
        "lastName": "Kim",
        "migrated": false,
        "migratedDate": "Fri Jul 09 2021 15:23:52 GMT-0500 (Colombia Standard Time)"
      },
      {
        "id": "c4490d96-96d2-43a7-997a-1d94144bd190",
        "userId": 869,
        "email": "user869@testmail.com",
        "userName": "test869",
        "firstName": "Nieves",
        "lastName": "Aguilar",
        "migrated": true,
        "migratedDate": "Sat Feb 29 2020 05:13:17 GMT-0500 (Colombia Standard Time)"
      },
      {
        "id": "8acc9072-c4e1-458e-9458-8e10d69d5fa8",
        "userId": 870,
        "email": "user870@testmail.com",
        "userName": "test870",
        "firstName": "Millie",
        "lastName": "Parrish",
        "migrated": true,
        "migratedDate": "Sun May 30 2021 18:11:19 GMT-0500 (Colombia Standard Time)"
      },
      {
        "id": "10806f02-fa7b-41eb-a11b-4a3a72582b0e",
        "userId": 871,
        "email": "user871@testmail.com",
        "userName": "test871",
        "firstName": "Robertson",
        "lastName": "Franklin",
        "migrated": true,
        "migratedDate": "Tue Jun 22 2021 16:51:06 GMT-0500 (Colombia Standard Time)"
      },
      {
        "id": "c9ecc506-358d-45c7-95a1-8d53c01e3d2f",
        "userId": 872,
        "email": "user872@testmail.com",
        "userName": "test872",
        "firstName": "Edwina",
        "lastName": "Allison",
        "migrated": false,
        "migratedDate": "Wed Feb 19 2020 08:01:03 GMT-0500 (Colombia Standard Time)"
      },
      {
        "id": "af749e91-971e-454d-8a41-3ab4ed4f0c4a",
        "userId": 873,
        "email": "user873@testmail.com",
        "userName": "test873",
        "firstName": "Dodson",
        "lastName": "Malone",
        "migrated": true,
        "migratedDate": "Tue Jun 29 2021 03:56:09 GMT-0500 (Colombia Standard Time)"
      },
      {
        "id": "2fe7283b-2ca2-495c-82fa-72d6561e9712",
        "userId": 874,
        "email": "user874@testmail.com",
        "userName": "test874",
        "firstName": "Burt",
        "lastName": "Moss",
        "migrated": false,
        "migratedDate": "Sat May 09 2020 17:29:10 GMT-0500 (Colombia Standard Time)"
      }
    ]
  }
}